{
  "MSE": 0.0002412604052169627,
  "MAE": 0.010348374690162018,
  "Max_Error": 0.2681162357330322,
  "Train_Error": 9.228853487002198e-05,
  "config": {
    "// Universal ODE operator configuration file": "config_ODE.json",
    "// Supported operator types": [
      "Inverse",
      "Homogeneous",
      "Nonlinear",
      "Custom"
    ],
    "// Data generation parameters": "",
    "num_train": 200,
    "num_test": 1000,
    "num_points": 100,
    "train_sample_num": 10,
    "test_sample_num": 100,
    "length_scale": 0.2,
    "num_cal": 1000,
    "// Model parameters": "",
    "branch_input_size": 100,
    "trunk_input_size": 1,
    "output_size": 1,
    "num_qubits": 5,
    "net_size": [
      20,
      2,
      10,
      2
    ],
    "scale_coeff": 0.001,
    "model_type": "QuanONet",
    "if_trainable_freq": true,
    "// Training parameters": "",
    "if_save": true,
    "if_keep": false,
    "if_train": true,
    "if_pi": false,
    "init_checkpoint": null,
    "operator_type": "Nonlinear",
    "if_adjust_lr": false,
    "learning_rate": 0.0001,
    "num_epochs": 5000,
    "target_error": 1e-10,
    "batch_size": 100,
    "validation_split": 0,
    "patience": 20,
    "// Operator-specific parameters": "",
    "custom_name": null,
    "custom_ode_description": "Only used when operator_type=Custom, specify via command line --custom_ode",
    "random_seed": 0
  },
  "training_history": [
    {
      "epoch": 0,
      "train_loss": 0.1513476338237524
    },
    {
      "epoch": 10,
      "train_loss": 0.03867844622582197
    },
    {
      "epoch": 20,
      "train_loss": 0.0359082649461925
    },
    {
      "epoch": 30,
      "train_loss": 0.03514141608029604
    },
    {
      "epoch": 40,
      "train_loss": 0.03408093927428126
    },
    {
      "epoch": 50,
      "train_loss": 0.031816492043435576
    },
    {
      "epoch": 60,
      "train_loss": 0.027543890196830033
    },
    {
      "epoch": 70,
      "train_loss": 0.020083876326680183
    },
    {
      "epoch": 80,
      "train_loss": 0.013227047398686409
    },
    {
      "epoch": 90,
      "train_loss": 0.010525828460231423
    },
    {
      "epoch": 100,
      "train_loss": 0.009855094295926393
    },
    {
      "epoch": 110,
      "train_loss": 0.00970760036725551
    },
    {
      "epoch": 120,
      "train_loss": 0.00959608000703156
    },
    {
      "epoch": 130,
      "train_loss": 0.00951562225818634
    },
    {
      "epoch": 140,
      "train_loss": 0.009448412503115833
    },
    {
      "epoch": 150,
      "train_loss": 0.009351300750859081
    },
    {
      "epoch": 160,
      "train_loss": 0.009250961290672422
    },
    {
      "epoch": 170,
      "train_loss": 0.00926072890870273
    },
    {
      "epoch": 180,
      "train_loss": 0.00917958163190633
    },
    {
      "epoch": 190,
      "train_loss": 0.008972866903059184
    },
    {
      "epoch": 200,
      "train_loss": 0.008888570754788817
    },
    {
      "epoch": 210,
      "train_loss": 0.00873595355078578
    },
    {
      "epoch": 220,
      "train_loss": 0.008624884276650846
    },
    {
      "epoch": 230,
      "train_loss": 0.008421175088733435
    },
    {
      "epoch": 240,
      "train_loss": 0.008297562482766807
    },
    {
      "epoch": 250,
      "train_loss": 0.008111891755834221
    },
    {
      "epoch": 260,
      "train_loss": 0.007906152866780758
    },
    {
      "epoch": 270,
      "train_loss": 0.007673760992474854
    },
    {
      "epoch": 280,
      "train_loss": 0.007370252418331802
    },
    {
      "epoch": 290,
      "train_loss": 0.007106367405503989
    },
    {
      "epoch": 300,
      "train_loss": 0.006734133907593786
    },
    {
      "epoch": 310,
      "train_loss": 0.006425804691389203
    },
    {
      "epoch": 320,
      "train_loss": 0.006097879004664719
    },
    {
      "epoch": 330,
      "train_loss": 0.005664750875439495
    },
    {
      "epoch": 340,
      "train_loss": 0.005151475430466235
    },
    {
      "epoch": 350,
      "train_loss": 0.004729853942990303
    },
    {
      "epoch": 360,
      "train_loss": 0.004352318192832172
    },
    {
      "epoch": 370,
      "train_loss": 0.004000445746351033
    },
    {
      "epoch": 380,
      "train_loss": 0.0036357659264467657
    },
    {
      "epoch": 390,
      "train_loss": 0.0033876119763590396
    },
    {
      "epoch": 400,
      "train_loss": 0.00318449855549261
    },
    {
      "epoch": 410,
      "train_loss": 0.003061545197851956
    },
    {
      "epoch": 420,
      "train_loss": 0.0028764642542228104
    },
    {
      "epoch": 430,
      "train_loss": 0.0027930889977142216
    },
    {
      "epoch": 440,
      "train_loss": 0.0027509632636792958
    },
    {
      "epoch": 450,
      "train_loss": 0.0026959859882481397
    },
    {
      "epoch": 460,
      "train_loss": 0.0026980621390976013
    },
    {
      "epoch": 470,
      "train_loss": 0.0026367938960902395
    },
    {
      "epoch": 480,
      "train_loss": 0.0026469528733287007
    },
    {
      "epoch": 490,
      "train_loss": 0.002631139598088339
    },
    {
      "epoch": 500,
      "train_loss": 0.0025761134456843138
    },
    {
      "epoch": 510,
      "train_loss": 0.0025358742452226577
    },
    {
      "epoch": 520,
      "train_loss": 0.0025542533898260445
    },
    {
      "epoch": 530,
      "train_loss": 0.002547269396018237
    },
    {
      "epoch": 540,
      "train_loss": 0.0025053742050658912
    },
    {
      "epoch": 550,
      "train_loss": 0.0025174310663715004
    },
    {
      "epoch": 560,
      "train_loss": 0.002445864386390895
    },
    {
      "epoch": 570,
      "train_loss": 0.0025806060410104694
    },
    {
      "epoch": 580,
      "train_loss": 0.0024492253549396993
    },
    {
      "epoch": 590,
      "train_loss": 0.002476100984495133
    },
    {
      "epoch": 600,
      "train_loss": 0.002397156727965921
    },
    {
      "epoch": 610,
      "train_loss": 0.002427034097490832
    },
    {
      "epoch": 620,
      "train_loss": 0.002358088607434183
    },
    {
      "epoch": 630,
      "train_loss": 0.0023821798444259913
    },
    {
      "epoch": 640,
      "train_loss": 0.002334247372345999
    },
    {
      "epoch": 650,
      "train_loss": 0.0023667398432735353
    },
    {
      "epoch": 660,
      "train_loss": 0.0023598651983775198
    },
    {
      "epoch": 670,
      "train_loss": 0.0022976951324380933
    },
    {
      "epoch": 680,
      "train_loss": 0.002280948165571317
    },
    {
      "epoch": 690,
      "train_loss": 0.0023201761592645197
    },
    {
      "epoch": 700,
      "train_loss": 0.002277810440864414
    },
    {
      "epoch": 710,
      "train_loss": 0.0022208129754289984
    },
    {
      "epoch": 720,
      "train_loss": 0.0022440799220930785
    },
    {
      "epoch": 730,
      "train_loss": 0.002173588384175673
    },
    {
      "epoch": 740,
      "train_loss": 0.0021300835185684265
    },
    {
      "epoch": 750,
      "train_loss": 0.002172609360422939
    },
    {
      "epoch": 760,
      "train_loss": 0.002106853004079312
    },
    {
      "epoch": 770,
      "train_loss": 0.0020925962424371393
    },
    {
      "epoch": 780,
      "train_loss": 0.0020821353362407537
    },
    {
      "epoch": 790,
      "train_loss": 0.002078301564324647
    },
    {
      "epoch": 800,
      "train_loss": 0.0020386115531437097
    },
    {
      "epoch": 810,
      "train_loss": 0.002056190092116594
    },
    {
      "epoch": 820,
      "train_loss": 0.0019543514295946806
    },
    {
      "epoch": 830,
      "train_loss": 0.00196788422181271
    },
    {
      "epoch": 840,
      "train_loss": 0.0019081203150562941
    },
    {
      "epoch": 850,
      "train_loss": 0.001880019874079153
    },
    {
      "epoch": 860,
      "train_loss": 0.0018972538993693889
    },
    {
      "epoch": 870,
      "train_loss": 0.0018549875123426319
    },
    {
      "epoch": 880,
      "train_loss": 0.001787929137935862
    },
    {
      "epoch": 890,
      "train_loss": 0.0017855061159934849
    },
    {
      "epoch": 900,
      "train_loss": 0.0017420484684407711
    },
    {
      "epoch": 910,
      "train_loss": 0.0017051176982931793
    },
    {
      "epoch": 920,
      "train_loss": 0.0016606822784524411
    },
    {
      "epoch": 930,
      "train_loss": 0.001653475739294663
    },
    {
      "epoch": 940,
      "train_loss": 0.0016154749086126686
    },
    {
      "epoch": 950,
      "train_loss": 0.0015809897740837187
    },
    {
      "epoch": 960,
      "train_loss": 0.0015671357105020434
    },
    {
      "epoch": 970,
      "train_loss": 0.0015057871700264514
    },
    {
      "epoch": 980,
      "train_loss": 0.0014789646898861974
    },
    {
      "epoch": 990,
      "train_loss": 0.0014478377648629247
    },
    {
      "epoch": 1000,
      "train_loss": 0.0014056324725970626
    },
    {
      "epoch": 1010,
      "train_loss": 0.0013652923458721488
    },
    {
      "epoch": 1020,
      "train_loss": 0.00134753726888448
    },
    {
      "epoch": 1030,
      "train_loss": 0.0013248582516098395
    },
    {
      "epoch": 1040,
      "train_loss": 0.0012733148178085685
    },
    {
      "epoch": 1050,
      "train_loss": 0.0012428491027094424
    },
    {
      "epoch": 1060,
      "train_loss": 0.0011900236335350201
    },
    {
      "epoch": 1070,
      "train_loss": 0.0011932296445593237
    },
    {
      "epoch": 1080,
      "train_loss": 0.0011328422930091619
    },
    {
      "epoch": 1090,
      "train_loss": 0.0011143572221044451
    },
    {
      "epoch": 1100,
      "train_loss": 0.0011004476429661736
    },
    {
      "epoch": 1110,
      "train_loss": 0.0010447087639477103
    },
    {
      "epoch": 1120,
      "train_loss": 0.0010436305165058002
    },
    {
      "epoch": 1130,
      "train_loss": 0.0009815783589147032
    },
    {
      "epoch": 1140,
      "train_loss": 0.0009594489471055567
    },
    {
      "epoch": 1150,
      "train_loss": 0.0009514526056591422
    },
    {
      "epoch": 1160,
      "train_loss": 0.0009188599593471736
    },
    {
      "epoch": 1170,
      "train_loss": 0.0009010119421873242
    },
    {
      "epoch": 1180,
      "train_loss": 0.0008642928587505594
    },
    {
      "epoch": 1190,
      "train_loss": 0.0008828983991406858
    },
    {
      "epoch": 1200,
      "train_loss": 0.0008303470094688237
    },
    {
      "epoch": 1210,
      "train_loss": 0.0008284245821414515
    },
    {
      "epoch": 1220,
      "train_loss": 0.000823860679520294
    },
    {
      "epoch": 1230,
      "train_loss": 0.0007910234242444858
    },
    {
      "epoch": 1240,
      "train_loss": 0.000795308779925108
    },
    {
      "epoch": 1250,
      "train_loss": 0.0007803994201822206
    },
    {
      "epoch": 1260,
      "train_loss": 0.0007766222261125222
    },
    {
      "epoch": 1270,
      "train_loss": 0.0007646001700777561
    },
    {
      "epoch": 1280,
      "train_loss": 0.0007790505391312763
    },
    {
      "epoch": 1290,
      "train_loss": 0.0007407234603306279
    },
    {
      "epoch": 1300,
      "train_loss": 0.0007733366568572819
    },
    {
      "epoch": 1310,
      "train_loss": 0.0007371467305347324
    },
    {
      "epoch": 1320,
      "train_loss": 0.0007407689598039723
    },
    {
      "epoch": 1330,
      "train_loss": 0.0007127811870304868
    },
    {
      "epoch": 1340,
      "train_loss": 0.0007122495357180014
    },
    {
      "epoch": 1350,
      "train_loss": 0.0007084450277034193
    },
    {
      "epoch": 1360,
      "train_loss": 0.0007094043714459986
    },
    {
      "epoch": 1370,
      "train_loss": 0.0007071937841828912
    },
    {
      "epoch": 1380,
      "train_loss": 0.0006976605072850361
    },
    {
      "epoch": 1390,
      "train_loss": 0.0007235783050418831
    },
    {
      "epoch": 1400,
      "train_loss": 0.0006828542813309468
    },
    {
      "epoch": 1410,
      "train_loss": 0.0006713266149745323
    },
    {
      "epoch": 1420,
      "train_loss": 0.0006800280389143154
    },
    {
      "epoch": 1430,
      "train_loss": 0.0006955994409509003
    },
    {
      "epoch": 1440,
      "train_loss": 0.0006786333135096357
    },
    {
      "epoch": 1450,
      "train_loss": 0.0006637763814069331
    },
    {
      "epoch": 1460,
      "train_loss": 0.0006856511332443916
    },
    {
      "epoch": 1470,
      "train_loss": 0.0006547614961164072
    },
    {
      "epoch": 1480,
      "train_loss": 0.0006713240378303454
    },
    {
      "epoch": 1490,
      "train_loss": 0.0006734094320563599
    },
    {
      "epoch": 1500,
      "train_loss": 0.0006432374299038202
    },
    {
      "epoch": 1510,
      "train_loss": 0.0006545716620166786
    },
    {
      "epoch": 1520,
      "train_loss": 0.0006341309970594011
    },
    {
      "epoch": 1530,
      "train_loss": 0.0006400623271474615
    },
    {
      "epoch": 1540,
      "train_loss": 0.0006415953379473649
    },
    {
      "epoch": 1550,
      "train_loss": 0.000631585723021999
    },
    {
      "epoch": 1560,
      "train_loss": 0.0006297257452388294
    },
    {
      "epoch": 1570,
      "train_loss": 0.000633310760895256
    },
    {
      "epoch": 1580,
      "train_loss": 0.0006194096378749237
    },
    {
      "epoch": 1590,
      "train_loss": 0.0006189311287016607
    },
    {
      "epoch": 1600,
      "train_loss": 0.0006236876884941012
    },
    {
      "epoch": 1610,
      "train_loss": 0.0006116630713222549
    },
    {
      "epoch": 1620,
      "train_loss": 0.0006204957200679928
    },
    {
      "epoch": 1630,
      "train_loss": 0.0006016554470988922
    },
    {
      "epoch": 1640,
      "train_loss": 0.0006274036815739237
    },
    {
      "epoch": 1650,
      "train_loss": 0.0005975212930934504
    },
    {
      "epoch": 1660,
      "train_loss": 0.0006002761496347375
    },
    {
      "epoch": 1670,
      "train_loss": 0.0006255823886021971
    },
    {
      "epoch": 1680,
      "train_loss": 0.0005934474625973962
    },
    {
      "epoch": 1690,
      "train_loss": 0.000587347945838701
    },
    {
      "epoch": 1700,
      "train_loss": 0.0005963154457276687
    },
    {
      "epoch": 1710,
      "train_loss": 0.0005757290258770808
    },
    {
      "epoch": 1720,
      "train_loss": 0.0005739722822909243
    },
    {
      "epoch": 1730,
      "train_loss": 0.0005833955205162056
    },
    {
      "epoch": 1740,
      "train_loss": 0.0005822259961860254
    },
    {
      "epoch": 1750,
      "train_loss": 0.0005751327844336629
    },
    {
      "epoch": 1760,
      "train_loss": 0.0005766787668108009
    },
    {
      "epoch": 1770,
      "train_loss": 0.0005623488905257545
    },
    {
      "epoch": 1780,
      "train_loss": 0.000558879152231384
    },
    {
      "epoch": 1790,
      "train_loss": 0.0005665424338076264
    },
    {
      "epoch": 1800,
      "train_loss": 0.0005586556711932644
    },
    {
      "epoch": 1810,
      "train_loss": 0.0005571203379076906
    },
    {
      "epoch": 1820,
      "train_loss": 0.0005684953430318274
    },
    {
      "epoch": 1830,
      "train_loss": 0.0005614847206743435
    },
    {
      "epoch": 1840,
      "train_loss": 0.000564361031865701
    },
    {
      "epoch": 1850,
      "train_loss": 0.0005366161902202293
    },
    {
      "epoch": 1860,
      "train_loss": 0.000565967925649602
    },
    {
      "epoch": 1870,
      "train_loss": 0.0005382026065490209
    },
    {
      "epoch": 1880,
      "train_loss": 0.0005350216219085268
    },
    {
      "epoch": 1890,
      "train_loss": 0.0005384512260206975
    },
    {
      "epoch": 1900,
      "train_loss": 0.0005374572749133222
    },
    {
      "epoch": 1910,
      "train_loss": 0.000528980053786654
    },
    {
      "epoch": 1920,
      "train_loss": 0.000551447861653287
    },
    {
      "epoch": 1930,
      "train_loss": 0.0005260460238787346
    },
    {
      "epoch": 1940,
      "train_loss": 0.0005172289529582486
    },
    {
      "epoch": 1950,
      "train_loss": 0.0005414373707026243
    },
    {
      "epoch": 1960,
      "train_loss": 0.0005261853526462801
    },
    {
      "epoch": 1970,
      "train_loss": 0.000514895519881975
    },
    {
      "epoch": 1980,
      "train_loss": 0.0005115210282383486
    },
    {
      "epoch": 1990,
      "train_loss": 0.000519936547789257
    },
    {
      "epoch": 2000,
      "train_loss": 0.0005236500641331076
    },
    {
      "epoch": 2010,
      "train_loss": 0.0005325950929545798
    },
    {
      "epoch": 2020,
      "train_loss": 0.0005192530545173213
    },
    {
      "epoch": 2030,
      "train_loss": 0.0005003548067179509
    },
    {
      "epoch": 2040,
      "train_loss": 0.0005008170468499884
    },
    {
      "epoch": 2050,
      "train_loss": 0.0004968011475284584
    },
    {
      "epoch": 2060,
      "train_loss": 0.0004891684890026227
    },
    {
      "epoch": 2070,
      "train_loss": 0.0005141417117556557
    },
    {
      "epoch": 2080,
      "train_loss": 0.0004808210112969391
    },
    {
      "epoch": 2090,
      "train_loss": 0.00048632214602548627
    },
    {
      "epoch": 2100,
      "train_loss": 0.0004859729378949851
    },
    {
      "epoch": 2110,
      "train_loss": 0.0004957982266205363
    },
    {
      "epoch": 2120,
      "train_loss": 0.00047692304651718586
    },
    {
      "epoch": 2130,
      "train_loss": 0.000489610162912868
    },
    {
      "epoch": 2140,
      "train_loss": 0.000489794545865152
    },
    {
      "epoch": 2150,
      "train_loss": 0.00048747817636467515
    },
    {
      "epoch": 2160,
      "train_loss": 0.0004664846608648077
    },
    {
      "epoch": 2170,
      "train_loss": 0.0004743163473904133
    },
    {
      "epoch": 2180,
      "train_loss": 0.0004666983775678091
    },
    {
      "epoch": 2190,
      "train_loss": 0.00045573756797239183
    },
    {
      "epoch": 2200,
      "train_loss": 0.00046905052149668334
    },
    {
      "epoch": 2210,
      "train_loss": 0.00046881103480700403
    },
    {
      "epoch": 2220,
      "train_loss": 0.000459109635266941
    },
    {
      "epoch": 2230,
      "train_loss": 0.00045242328342283146
    },
    {
      "epoch": 2240,
      "train_loss": 0.00045815240155206994
    },
    {
      "epoch": 2250,
      "train_loss": 0.0004500920345890336
    },
    {
      "epoch": 2260,
      "train_loss": 0.0004371449307654984
    },
    {
      "epoch": 2270,
      "train_loss": 0.0004465736710699275
    },
    {
      "epoch": 2280,
      "train_loss": 0.00044383084314176814
    },
    {
      "epoch": 2290,
      "train_loss": 0.0004317461236496456
    },
    {
      "epoch": 2300,
      "train_loss": 0.0004311790165957063
    },
    {
      "epoch": 2310,
      "train_loss": 0.0004264105482434388
    },
    {
      "epoch": 2320,
      "train_loss": 0.00042057894897880034
    },
    {
      "epoch": 2330,
      "train_loss": 0.0004348882372141816
    },
    {
      "epoch": 2340,
      "train_loss": 0.0004492961161304265
    },
    {
      "epoch": 2350,
      "train_loss": 0.00043609428976196794
    },
    {
      "epoch": 2360,
      "train_loss": 0.00042455729853827504
    },
    {
      "epoch": 2370,
      "train_loss": 0.00041944147960748523
    },
    {
      "epoch": 2380,
      "train_loss": 0.00042433395137777554
    },
    {
      "epoch": 2390,
      "train_loss": 0.00041300999728264285
    },
    {
      "epoch": 2400,
      "train_loss": 0.0003985096860560589
    },
    {
      "epoch": 2410,
      "train_loss": 0.0003963524897699244
    },
    {
      "epoch": 2420,
      "train_loss": 0.0003946550525142811
    },
    {
      "epoch": 2430,
      "train_loss": 0.00040245112759293986
    },
    {
      "epoch": 2440,
      "train_loss": 0.0004259131193975918
    },
    {
      "epoch": 2450,
      "train_loss": 0.00039218921010615305
    },
    {
      "epoch": 2460,
      "train_loss": 0.00038954090850893406
    },
    {
      "epoch": 2470,
      "train_loss": 0.0003840578370727599
    },
    {
      "epoch": 2480,
      "train_loss": 0.0003910322033334523
    },
    {
      "epoch": 2490,
      "train_loss": 0.0003905248231603764
    },
    {
      "epoch": 2500,
      "train_loss": 0.0003676414838992059
    },
    {
      "epoch": 2510,
      "train_loss": 0.0003699192136991769
    },
    {
      "epoch": 2520,
      "train_loss": 0.00037714429636253043
    },
    {
      "epoch": 2530,
      "train_loss": 0.0003687505071866326
    },
    {
      "epoch": 2540,
      "train_loss": 0.000364933573291637
    },
    {
      "epoch": 2550,
      "train_loss": 0.00037398622807813806
    },
    {
      "epoch": 2560,
      "train_loss": 0.00035503151593729854
    },
    {
      "epoch": 2570,
      "train_loss": 0.00035478470381349324
    },
    {
      "epoch": 2580,
      "train_loss": 0.0003632198538980447
    },
    {
      "epoch": 2590,
      "train_loss": 0.0003458283688814845
    },
    {
      "epoch": 2600,
      "train_loss": 0.00036251448036637155
    },
    {
      "epoch": 2610,
      "train_loss": 0.0003468413488008082
    },
    {
      "epoch": 2620,
      "train_loss": 0.0003572592162527144
    },
    {
      "epoch": 2630,
      "train_loss": 0.00033555346308276055
    },
    {
      "epoch": 2640,
      "train_loss": 0.0003397972395760007
    },
    {
      "epoch": 2650,
      "train_loss": 0.00032617130564176476
    },
    {
      "epoch": 2660,
      "train_loss": 0.0003456272257608362
    },
    {
      "epoch": 2670,
      "train_loss": 0.0003249082896218169
    },
    {
      "epoch": 2680,
      "train_loss": 0.0003275438575656153
    },
    {
      "epoch": 2690,
      "train_loss": 0.0003138411550025921
    },
    {
      "epoch": 2700,
      "train_loss": 0.0003131375582597684
    },
    {
      "epoch": 2710,
      "train_loss": 0.0003059885864786338
    },
    {
      "epoch": 2720,
      "train_loss": 0.0003195276229234878
    },
    {
      "epoch": 2730,
      "train_loss": 0.00030463625880656765
    },
    {
      "epoch": 2740,
      "train_loss": 0.00030185047799022866
    },
    {
      "epoch": 2750,
      "train_loss": 0.00030074111418798566
    },
    {
      "epoch": 2760,
      "train_loss": 0.0002972316695377231
    },
    {
      "epoch": 2770,
      "train_loss": 0.00032310853130184113
    },
    {
      "epoch": 2780,
      "train_loss": 0.0002997319446876645
    },
    {
      "epoch": 2790,
      "train_loss": 0.00029872387312934734
    },
    {
      "epoch": 2800,
      "train_loss": 0.0003185184112226125
    },
    {
      "epoch": 2810,
      "train_loss": 0.0002888940252887551
    },
    {
      "epoch": 2820,
      "train_loss": 0.00028435386993805876
    },
    {
      "epoch": 2830,
      "train_loss": 0.00027425834923633374
    },
    {
      "epoch": 2840,
      "train_loss": 0.0002843833957740571
    },
    {
      "epoch": 2850,
      "train_loss": 0.0002737228445766959
    },
    {
      "epoch": 2860,
      "train_loss": 0.0002748421386058908
    },
    {
      "epoch": 2870,
      "train_loss": 0.00027501098593347707
    },
    {
      "epoch": 2880,
      "train_loss": 0.00026765959337353705
    },
    {
      "epoch": 2890,
      "train_loss": 0.00026277921933797187
    },
    {
      "epoch": 2900,
      "train_loss": 0.00025844854390015825
    },
    {
      "epoch": 2910,
      "train_loss": 0.0002580699678219389
    },
    {
      "epoch": 2920,
      "train_loss": 0.0002523318282328546
    },
    {
      "epoch": 2930,
      "train_loss": 0.000248500365705695
    },
    {
      "epoch": 2940,
      "train_loss": 0.0002499342575902119
    },
    {
      "epoch": 2950,
      "train_loss": 0.00025030496617546306
    },
    {
      "epoch": 2960,
      "train_loss": 0.00024648231046739964
    },
    {
      "epoch": 2970,
      "train_loss": 0.00025722520294948483
    },
    {
      "epoch": 2980,
      "train_loss": 0.00024966204873635436
    },
    {
      "epoch": 2990,
      "train_loss": 0.00023116990196285768
    },
    {
      "epoch": 3000,
      "train_loss": 0.0002377962133323308
    },
    {
      "epoch": 3010,
      "train_loss": 0.000227389299107017
    },
    {
      "epoch": 3020,
      "train_loss": 0.00022372358580469154
    },
    {
      "epoch": 3030,
      "train_loss": 0.0002264246271806769
    },
    {
      "epoch": 3040,
      "train_loss": 0.00022696758460369893
    },
    {
      "epoch": 3050,
      "train_loss": 0.00021713977039325983
    },
    {
      "epoch": 3060,
      "train_loss": 0.0002188715836382471
    },
    {
      "epoch": 3070,
      "train_loss": 0.00021645497836288995
    },
    {
      "epoch": 3080,
      "train_loss": 0.00021478791168192402
    },
    {
      "epoch": 3090,
      "train_loss": 0.00020748899405589327
    },
    {
      "epoch": 3100,
      "train_loss": 0.00020455345220398157
    },
    {
      "epoch": 3110,
      "train_loss": 0.00020840501310885883
    },
    {
      "epoch": 3120,
      "train_loss": 0.00021154079076950437
    },
    {
      "epoch": 3130,
      "train_loss": 0.000198821635422064
    },
    {
      "epoch": 3140,
      "train_loss": 0.0002010925432841759
    },
    {
      "epoch": 3150,
      "train_loss": 0.00019418030424276367
    },
    {
      "epoch": 3160,
      "train_loss": 0.00019272788558737374
    },
    {
      "epoch": 3170,
      "train_loss": 0.00018979051092173904
    },
    {
      "epoch": 3180,
      "train_loss": 0.00019374611583771183
    },
    {
      "epoch": 3190,
      "train_loss": 0.00018775282151182183
    },
    {
      "epoch": 3200,
      "train_loss": 0.00018230094501632267
    },
    {
      "epoch": 3210,
      "train_loss": 0.00018033001324511134
    },
    {
      "epoch": 3220,
      "train_loss": 0.00017950808614841662
    },
    {
      "epoch": 3230,
      "train_loss": 0.0001795577998564113
    },
    {
      "epoch": 3240,
      "train_loss": 0.00017376742471242324
    },
    {
      "epoch": 3250,
      "train_loss": 0.0001824049679271411
    },
    {
      "epoch": 3260,
      "train_loss": 0.00018491764640202746
    },
    {
      "epoch": 3270,
      "train_loss": 0.00017880477680591865
    },
    {
      "epoch": 3280,
      "train_loss": 0.00016768900422903243
    },
    {
      "epoch": 3290,
      "train_loss": 0.00017661289166426286
    },
    {
      "epoch": 3300,
      "train_loss": 0.00017529775723232888
    },
    {
      "epoch": 3310,
      "train_loss": 0.00016499567027494777
    },
    {
      "epoch": 3320,
      "train_loss": 0.00016787235799711197
    },
    {
      "epoch": 3330,
      "train_loss": 0.00017562958673806862
    },
    {
      "epoch": 3340,
      "train_loss": 0.00016139953695528674
    },
    {
      "epoch": 3350,
      "train_loss": 0.00016715024976292624
    },
    {
      "epoch": 3360,
      "train_loss": 0.00016553499081055633
    },
    {
      "epoch": 3370,
      "train_loss": 0.00016135078039951621
    },
    {
      "epoch": 3380,
      "train_loss": 0.00015569303504889831
    },
    {
      "epoch": 3390,
      "train_loss": 0.00015424098892253825
    },
    {
      "epoch": 3400,
      "train_loss": 0.00015899775535217487
    },
    {
      "epoch": 3410,
      "train_loss": 0.0001542605103168171
    },
    {
      "epoch": 3420,
      "train_loss": 0.00015453504456672818
    },
    {
      "epoch": 3430,
      "train_loss": 0.00014887173201714177
    },
    {
      "epoch": 3440,
      "train_loss": 0.00017270446260226892
    },
    {
      "epoch": 3450,
      "train_loss": 0.0001498220553912688
    },
    {
      "epoch": 3460,
      "train_loss": 0.00014714184544573072
    },
    {
      "epoch": 3470,
      "train_loss": 0.00014509103457385208
    },
    {
      "epoch": 3480,
      "train_loss": 0.00014466107422776985
    },
    {
      "epoch": 3490,
      "train_loss": 0.00015106072096386923
    },
    {
      "epoch": 3500,
      "train_loss": 0.00014370770513778553
    },
    {
      "epoch": 3510,
      "train_loss": 0.00014615793224947993
    },
    {
      "epoch": 3520,
      "train_loss": 0.00014887735887896268
    },
    {
      "epoch": 3530,
      "train_loss": 0.00014192338567227126
    },
    {
      "epoch": 3540,
      "train_loss": 0.00014425917688640766
    },
    {
      "epoch": 3550,
      "train_loss": 0.0001399591586960014
    },
    {
      "epoch": 3560,
      "train_loss": 0.00013946007129561622
    },
    {
      "epoch": 3570,
      "train_loss": 0.00014409515606530476
    },
    {
      "epoch": 3580,
      "train_loss": 0.00013511699180526193
    },
    {
      "epoch": 3590,
      "train_loss": 0.00013654607246280648
    },
    {
      "epoch": 3600,
      "train_loss": 0.0001416881426848704
    },
    {
      "epoch": 3610,
      "train_loss": 0.00014451812130573672
    },
    {
      "epoch": 3620,
      "train_loss": 0.00013681613490916787
    },
    {
      "epoch": 3630,
      "train_loss": 0.0001416699687979417
    },
    {
      "epoch": 3640,
      "train_loss": 0.00014013127401995006
    },
    {
      "epoch": 3650,
      "train_loss": 0.0001428596984624164
    },
    {
      "epoch": 3660,
      "train_loss": 0.0001395233630319126
    },
    {
      "epoch": 3670,
      "train_loss": 0.00013105600519338622
    },
    {
      "epoch": 3680,
      "train_loss": 0.00013224417707533576
    },
    {
      "epoch": 3690,
      "train_loss": 0.00012966500689799433
    },
    {
      "epoch": 3700,
      "train_loss": 0.00013610485002573113
    },
    {
      "epoch": 3710,
      "train_loss": 0.0001298628416407155
    },
    {
      "epoch": 3720,
      "train_loss": 0.00014582121475541497
    },
    {
      "epoch": 3730,
      "train_loss": 0.0001347155623079743
    },
    {
      "epoch": 3740,
      "train_loss": 0.0001311137541051721
    },
    {
      "epoch": 3750,
      "train_loss": 0.000136813935750979
    },
    {
      "epoch": 3760,
      "train_loss": 0.00012464138344512322
    },
    {
      "epoch": 3770,
      "train_loss": 0.00012787691157427615
    },
    {
      "epoch": 3780,
      "train_loss": 0.00013238756255304907
    },
    {
      "epoch": 3790,
      "train_loss": 0.00012377273851598146
    },
    {
      "epoch": 3800,
      "train_loss": 0.0001274762016691966
    },
    {
      "epoch": 3810,
      "train_loss": 0.00013019131620239932
    },
    {
      "epoch": 3820,
      "train_loss": 0.00012461968581192195
    },
    {
      "epoch": 3830,
      "train_loss": 0.00013826763824908994
    },
    {
      "epoch": 3840,
      "train_loss": 0.00012557847039715853
    },
    {
      "epoch": 3850,
      "train_loss": 0.00012449765927158296
    },
    {
      "epoch": 3860,
      "train_loss": 0.00012148790956416633
    },
    {
      "epoch": 3870,
      "train_loss": 0.0001254397790035
    },
    {
      "epoch": 3880,
      "train_loss": 0.00011954740948567632
    },
    {
      "epoch": 3890,
      "train_loss": 0.00012182602986285929
    },
    {
      "epoch": 3900,
      "train_loss": 0.00012071631026628893
    },
    {
      "epoch": 3910,
      "train_loss": 0.00012215037313580978
    },
    {
      "epoch": 3920,
      "train_loss": 0.00012261718802619725
    },
    {
      "epoch": 3930,
      "train_loss": 0.00012618945002031978
    },
    {
      "epoch": 3940,
      "train_loss": 0.00012304644951655064
    },
    {
      "epoch": 3950,
      "train_loss": 0.00013025318912696093
    },
    {
      "epoch": 3960,
      "train_loss": 0.00011853994656121358
    },
    {
      "epoch": 3970,
      "train_loss": 0.00011951841624977533
    },
    {
      "epoch": 3980,
      "train_loss": 0.00011448783734522295
    },
    {
      "epoch": 3990,
      "train_loss": 0.00011576480428630021
    },
    {
      "epoch": 4000,
      "train_loss": 0.00011751562742574606
    },
    {
      "epoch": 4010,
      "train_loss": 0.00011476388572191354
    },
    {
      "epoch": 4020,
      "train_loss": 0.00011585663378355093
    },
    {
      "epoch": 4030,
      "train_loss": 0.00011542419888428412
    },
    {
      "epoch": 4040,
      "train_loss": 0.00012133083218941465
    },
    {
      "epoch": 4050,
      "train_loss": 0.00011580496720853262
    },
    {
      "epoch": 4060,
      "train_loss": 0.0001200055303343106
    },
    {
      "epoch": 4070,
      "train_loss": 0.00011815438665507827
    },
    {
      "epoch": 4080,
      "train_loss": 0.00011778054649767001
    },
    {
      "epoch": 4090,
      "train_loss": 0.00011125608798465692
    },
    {
      "epoch": 4100,
      "train_loss": 0.00011833661592390854
    },
    {
      "epoch": 4110,
      "train_loss": 0.00011333722759445663
    },
    {
      "epoch": 4120,
      "train_loss": 0.0001127391449699644
    },
    {
      "epoch": 4130,
      "train_loss": 0.00011781661196437198
    },
    {
      "epoch": 4140,
      "train_loss": 0.00011274481621512678
    },
    {
      "epoch": 4150,
      "train_loss": 0.00011369539752195123
    },
    {
      "epoch": 4160,
      "train_loss": 0.00011523619032232091
    },
    {
      "epoch": 4170,
      "train_loss": 0.00011419513539294713
    },
    {
      "epoch": 4180,
      "train_loss": 0.00011061270197387785
    },
    {
      "epoch": 4190,
      "train_loss": 0.0001106956806324888
    },
    {
      "epoch": 4200,
      "train_loss": 0.00011076776863774284
    },
    {
      "epoch": 4210,
      "train_loss": 0.00011284899228485301
    },
    {
      "epoch": 4220,
      "train_loss": 0.00011146114447910805
    },
    {
      "epoch": 4230,
      "train_loss": 0.00010779861258924939
    },
    {
      "epoch": 4240,
      "train_loss": 0.00011065575563407037
    },
    {
      "epoch": 4250,
      "train_loss": 0.00011131572573503945
    },
    {
      "epoch": 4260,
      "train_loss": 0.00011266196452197619
    },
    {
      "epoch": 4270,
      "train_loss": 0.00010782369281514548
    },
    {
      "epoch": 4280,
      "train_loss": 0.00011844310101878363
    },
    {
      "epoch": 4290,
      "train_loss": 0.00011161179209011607
    },
    {
      "epoch": 4300,
      "train_loss": 0.0001098153992643347
    },
    {
      "epoch": 4310,
      "train_loss": 0.00010457381249580066
    },
    {
      "epoch": 4320,
      "train_loss": 0.00010911069366557058
    },
    {
      "epoch": 4330,
      "train_loss": 0.00010590672609396279
    },
    {
      "epoch": 4340,
      "train_loss": 0.00010566102064331062
    },
    {
      "epoch": 4350,
      "train_loss": 0.00011064790342061315
    },
    {
      "epoch": 4360,
      "train_loss": 0.00010477245486981702
    },
    {
      "epoch": 4370,
      "train_loss": 0.00010879777728405316
    },
    {
      "epoch": 4380,
      "train_loss": 0.00011818227030744311
    },
    {
      "epoch": 4390,
      "train_loss": 0.00010662296044756658
    },
    {
      "epoch": 4400,
      "train_loss": 0.00010653429017111193
    },
    {
      "epoch": 4410,
      "train_loss": 0.00010309160279575735
    },
    {
      "epoch": 4420,
      "train_loss": 0.00010419949794595595
    },
    {
      "epoch": 4430,
      "train_loss": 0.00010887799580814317
    },
    {
      "epoch": 4440,
      "train_loss": 0.00010665440022421535
    },
    {
      "epoch": 4450,
      "train_loss": 0.00010546083758526948
    },
    {
      "epoch": 4460,
      "train_loss": 0.0001089959350792924
    },
    {
      "epoch": 4470,
      "train_loss": 0.0001073702791472897
    },
    {
      "epoch": 4480,
      "train_loss": 0.00011164139141328633
    },
    {
      "epoch": 4490,
      "train_loss": 0.00010746975203801412
    },
    {
      "epoch": 4500,
      "train_loss": 0.0001055647782777669
    },
    {
      "epoch": 4510,
      "train_loss": 0.0001060157661413541
    },
    {
      "epoch": 4520,
      "train_loss": 0.00010308562123100274
    },
    {
      "epoch": 4530,
      "train_loss": 0.00010224268953606952
    },
    {
      "epoch": 4540,
      "train_loss": 0.00010950858304568101
    },
    {
      "epoch": 4550,
      "train_loss": 0.00010360789819969795
    },
    {
      "epoch": 4560,
      "train_loss": 0.00010024768380390014
    },
    {
      "epoch": 4570,
      "train_loss": 0.00010613927443046123
    },
    {
      "epoch": 4580,
      "train_loss": 0.00010405886750959325
    },
    {
      "epoch": 4590,
      "train_loss": 0.00010202221055806149
    },
    {
      "epoch": 4600,
      "train_loss": 9.890898909361567e-05
    },
    {
      "epoch": 4610,
      "train_loss": 0.00010182799451285973
    },
    {
      "epoch": 4620,
      "train_loss": 0.00010462298887432553
    },
    {
      "epoch": 4630,
      "train_loss": 0.00010251130079268478
    },
    {
      "epoch": 4640,
      "train_loss": 0.00010278738118358887
    },
    {
      "epoch": 4650,
      "train_loss": 9.975126777135301e-05
    },
    {
      "epoch": 4660,
      "train_loss": 0.00010324885515728965
    },
    {
      "epoch": 4670,
      "train_loss": 0.00010234440851490945
    },
    {
      "epoch": 4680,
      "train_loss": 9.583806640875992e-05
    },
    {
      "epoch": 4690,
      "train_loss": 0.0001044406890287064
    },
    {
      "epoch": 4700,
      "train_loss": 0.00010212408524239436
    },
    {
      "epoch": 4710,
      "train_loss": 9.711423263070174e-05
    },
    {
      "epoch": 4720,
      "train_loss": 0.00010459400436957367
    },
    {
      "epoch": 4730,
      "train_loss": 0.0001037722649925854
    },
    {
      "epoch": 4740,
      "train_loss": 9.589761721144896e-05
    },
    {
      "epoch": 4750,
      "train_loss": 9.572483850206481e-05
    },
    {
      "epoch": 4760,
      "train_loss": 9.740285495354328e-05
    },
    {
      "epoch": 4770,
      "train_loss": 0.00010226957529084757
    },
    {
      "epoch": 4780,
      "train_loss": 0.00010218304814770817
    },
    {
      "epoch": 4790,
      "train_loss": 9.557461817166768e-05
    },
    {
      "epoch": 4800,
      "train_loss": 0.00010137964054592885
    },
    {
      "epoch": 4810,
      "train_loss": 9.958677237591474e-05
    },
    {
      "epoch": 4820,
      "train_loss": 9.885248618957121e-05
    },
    {
      "epoch": 4830,
      "train_loss": 9.631203174649272e-05
    },
    {
      "epoch": 4840,
      "train_loss": 0.00011161536676809191
    },
    {
      "epoch": 4850,
      "train_loss": 9.914341317198704e-05
    },
    {
      "epoch": 4860,
      "train_loss": 9.688265090517234e-05
    },
    {
      "epoch": 4870,
      "train_loss": 0.00010389472408860456
    },
    {
      "epoch": 4880,
      "train_loss": 9.691731247585267e-05
    },
    {
      "epoch": 4890,
      "train_loss": 9.426570723007899e-05
    },
    {
      "epoch": 4900,
      "train_loss": 9.607706706447062e-05
    },
    {
      "epoch": 4910,
      "train_loss": 9.51923240791075e-05
    },
    {
      "epoch": 4920,
      "train_loss": 9.85299364401726e-05
    },
    {
      "epoch": 4930,
      "train_loss": 9.272132556361611e-05
    },
    {
      "epoch": 4940,
      "train_loss": 9.731880618346622e-05
    },
    {
      "epoch": 4950,
      "train_loss": 9.228853487002198e-05
    },
    {
      "epoch": 4960,
      "train_loss": 9.652295957494062e-05
    },
    {
      "epoch": 4970,
      "train_loss": 9.471635603404138e-05
    },
    {
      "epoch": 4980,
      "train_loss": 9.547495792503469e-05
    },
    {
      "epoch": 4990,
      "train_loss": 9.407242869201582e-05
    }
  ]
}